fusionMLlib/__init__.py
fusionmllib-0.1.0.dist-info/METADATA
fusionmllib-0.1.0.dist-info/WHEEL
fusionmllib-0.1.0.dist-info/top_level.txt
fusionmllib-0.1.0.dist-info/RECORD
