Metadata-Version: 2.2
Name: fusionMLlib
Version: 0.1.0
Summary: A one-stop ML meta-package for all essential libraries
Author: Your Name
Classifier: Programming Language :: Python :: 3
Classifier: Intended Audience :: Developers
Classifier: Topic :: Scientific/Engineering :: Artificial Intelligence
Requires-Python: >=3.7
Requires-Dist: numpy
Requires-Dist: pandas
Requires-Dist: scikit-learn
Requires-Dist: matplotlib
Requires-Dist: seaborn
Requires-Dist: xgboost
Requires-Dist: lightgbm
Requires-Dist: catboost
Requires-Dist: tensorflow
Requires-Dist: torch
Requires-Dist: transformers
Requires-Dist: statsmodels
Requires-Dist: dask
Requires-Dist: polars
Requires-Dist: nltk
Requires-Dist: spacy
Requires-Dist: gensim
Requires-Dist: opencv-python
Requires-Dist: torchvision
Requires-Dist: albumentations
Requires-Dist: mlflow
Requires-Dist: bentoml
Requires-Dist: fastapi
Requires-Dist: joblib
Requires-Dist: optuna
Requires-Dist: shap
Requires-Dist: lime
Requires-Dist: tqdm
Dynamic: author
Dynamic: classifier
Dynamic: requires-dist
Dynamic: requires-python
Dynamic: summary
